Compiled from "Strings.java"
public class rjvm.Strings {
  public rjvm.Strings();
    Code:
       0: aload_0
       1: invokespecial #1                  // Method java/lang/Object."<init>":()V
       4: return

  public static void main(java.lang.String[]);
    Code:
       0: ldc           #7                  // String Andrea
       2: sipush        1985
       5: invokestatic  #9                  // Method sayHello:(Ljava/lang/String;I)V
       8: return

  private static void sayHello(java.lang.String, int);
    Code:
       0: aload_0
       1: iload_1
       2: invokedynamic #15,  0             // InvokeDynamic #0:makeConcatWithConstants:(Ljava/lang/String;I)Ljava/lang/String;
       7: invokestatic  #19                 // Method tempPrint:(Ljava/lang/String;)V
      10: return

  private static native void tempPrint(java.lang.String);
}
